Workbook

Sheet Cover
C1: AMIR J
C4: TESLA, INC. (NASDAQ: TSLA)
C6: Applied DCF Valuation Model
C7: Valuation date: 30 June 2026 | All figures in USD millions unless stated
C11: Table of Contents
C13: Outputs
C14: Inputs
C15: Model
C22: Colour Convention
C23: Blue: hardcoded input | H23: Yellow fill marks key assumptions and headline outputs.
C24: Black: formula
C25: Green: link to another worksheet
C29: Primary Source
C30: Tesla Q4 and FY2025 Update and Q2 2026 Update, Tesla Investor Relations, ir.tesla.com
C31: Bloomberg (2026) Bloomberg Terminal. Bloomberg L.P.

Sheet Outputs
C1: AMIR J
C5: Dashboard: Perpetuity Growth Method
E8: Model Drivers Set To | G8: 2 | M8: All figures in USD millions unless stated
E11: Main Outputs | M11: Selected Inputs
G13: Enterprise | H13: Equity | I13: Equity
E14: Live (Current Switch) | G14: Value | H14: Value | I14: Per Share | M14: Terminal Growth Rate | P14: =Inputs!$G$142 -> 0.03
G15: =Model!$I$307 -> 616187.58 | H15: =G15-$P$16 -> 651870.58 | I15: =H15/$P$17 -> 183.88451 | M15: WACC | P15: =Inputs!$M$122 -> 0.078316088
E16: Best Case | F16: 1 | G16: 1443710.8 | H16: =G16-$P$16 -> 1479393.8 | I16: =H16/$P$17 -> 417.31841 | M16: Net Debt / (Net Cash) | O16: (End of 2025) | P16: =Inputs!$M$132 -> -35683
E17: Base Case | F17: 2 | G17: 616187.58 | H17: =G17-$P$16 -> 651870.58 | I17: =H17/$P$17 -> 183.88451 | M17: Shares Outstanding | O17: (FD, m) | P17: =Inputs!$G$140 -> 3545
E18: Worst Case | F18: 3 | G18: 181365.43 | H18: =G18-$P$16 -> 217048.43 | I18: =H18/$P$17 -> 61.226639 | M18: Current Share Price | O18: (US$/sh) | P18: =Inputs!$G$141 -> 309.22
E22: Enterprise Value | M22: Equity Value per Share
E24: Terminal Growth Rate | M24: Terminal Growth Rate
D25: =Model!$I$307 -> 616187.58 | E25: =F25-0.005 -> 0.02 | F25: =G25-0.005 -> 0.025 | G25: =Inputs!$G$142 -> 0.03 | H25: =G25+0.005 -> 0.035 | I25: =H25+0.005 -> 0.04 | M25: =E25 -> 0.02 | N25: =F25 -> 0.025 | O25: =G25 -> 0.03 | P25: =H25 -> 0.035 | Q25: =I25 -> 0.04
C26: WACC | D26: =D27-0.005 -> 0.068316088 | E26: 669146.16 | F26: 727940.16 | G26: 802078.62 | H26: 898470.14 | I26: 1028902.9 | K26: WACC | L26: =D26 -> 0.068316088 | M26: =E39/$P$17 -> 198.82346 | N26: =F39/$P$17 -> 215.40851 | O26: =G39/$P$17 -> 236.32204 | P26: =H39/$P$17 -> 263.51287 | Q26: =I39/$P$17 -> 300.30632
D27: =D28-0.005 -> 0.073316088 | E27: 596351.68 | F27: 642045.68 | G27: 698288.65 | H27: 769210.3 | I27: 861419.45 | L27: =D27 -> 0.073316088 | M27: =E40/$P$17 -> 178.28905 | N27: =F40/$P$17 -> 191.17875 | O27: =G40/$P$17 -> 207.04419 | P27: =H40/$P$17 -> 227.0503 | Q27: =I40/$P$17 -> 253.06134
D28: =Inputs!$M$122 -> 0.078316088 | E28: 536243.95 | F28: 572467.19 | G28: 616187.58 | H28: 670001.29 | I28: 737859.69 | L28: =D28 -> 0.078316088 | M28: =E41/$P$17 -> 161.33341 | N28: =F41/$P$17 -> 171.55154 | O28: =G41/$P$17 -> 183.88451 | P28: =H41/$P$17 -> 199.06468 | Q28: =I41/$P$17 -> 218.20668
D29: =D28+0.005 -> 0.083316088 | E29: 485811.69 | F29: 515002.42 | G29: 549668.19 | H29: 591508.74 | I29: 643008.65 | L29: =D29 -> 0.083316088 | M29: =E42/$P$17 -> 147.10711 | N29: =F42/$P$17 -> 155.34145 | O29: =G42/$P$17 -> 165.12022 | P29: =H42/$P$17 -> 176.92292 | Q29: =I42/$P$17 -> 191.45039
D30: =D29+0.005 -> 0.088316088 | E30: 442925.39 | F30: 466776.67 | G30: 494717.95 | H30: 527899.92 | I30: 567949.58 | L30: =D30 -> 0.088316088 | M30: =E43/$P$17 -> 135.00942 | N30: =F43/$P$17 -> 141.73757 | O30: =G43/$P$17 -> 149.61945 | P30: =H43/$P$17 -> 158.97967 | Q30: =I43/$P$17 -> 170.27717
E35: Equity Value | M35: Premium / (Discount) to Share Price
E37: Terminal Growth Rate | M37: Terminal Growth Rate
E38: =E25 -> 0.02 | F38: =F25 -> 0.025 | G38: =G25 -> 0.03 | H38: =H25 -> 0.035 | I38: =I25 -> 0.04 | M38: =E38 -> 0.02 | N38: =F38 -> 0.025 | O38: =G38 -> 0.03 | P38: =H38 -> 0.035 | Q38: =I38 -> 0.04
C39: WACC | D39: =D40-0.005 -> 0.068316088 | E39: =E26-$P$16 -> 704829.16 | F39: =F26-$P$16 -> 763623.16 | G39: =G26-$P$16 -> 837761.62 | H39: =H26-$P$16 -> 934153.14 | I39: =I26-$P$16 -> 1064585.9 | K39: WACC | L39: =D39 -> 0.068316088 | M39: =M26/$P$18-1 -> -0.35701618 | N39: =N26/$P$18-1 -> -0.30338107 | O39: =O26/$P$18-1 -> -0.23574789 | P39: =P26/$P$18-1 -> -0.14781426 | Q39: =Q26/$P$18-1 -> -0.028826332
D40: =D41-0.005 -> 0.073316088 | E40: =E27-$P$16 -> 632034.68 | F40: =F27-$P$16 -> 677728.68 | G40: =G27-$P$16 -> 733971.65 | H40: =H27-$P$16 -> 804893.3 | I40: =I27-$P$16 -> 897102.45 | L40: =D40 -> 0.073316088 | M40: =M27/$P$18-1 -> -0.42342329 | N40: =N27/$P$18-1 -> -0.38173872 | O40: =O27/$P$18-1 -> -0.3304308 | P40: =P27/$P$18-1 -> -0.26573218 | Q40: =Q27/$P$18-1 -> -0.18161393
D41: =D28 -> 0.078316088 | E41: =E28-$P$16 -> 571926.95 | F41: =F28-$P$16 -> 608150.19 | G41: =G28-$P$16 -> 651870.58 | H41: =H28-$P$16 -> 705684.29 | I41: =I28-$P$16 -> 773542.69 | L41: =D41 -> 0.078316088 | M41: =M28/$P$18-1 -> -0.47825686 | N41: =N28/$P$18-1 -> -0.44521203 | O41: =O28/$P$18-1 -> -0.4053279 | P41: =P28/$P$18-1 -> -0.35623608 | Q41: =Q28/$P$18-1 -> -0.29433193
D42: =D41+0.005 -> 0.083316088 | E42: =E29-$P$16 -> 521494.69 | F42: =F29-$P$16 -> 550685.42 | G42: =G29-$P$16 -> 585351.19 | H42: =H29-$P$16 -> 627191.74 | I42: =I29-$P$16 -> 678691.65 | L42: =D42 -> 0.083316088 | M42: =M29/$P$18-1 -> -0.52426394 | N42: =N29/$P$18-1 -> -0.49763455 | O42: =O29/$P$18-1 -> -0.46601054 | P42: =P29/$P$18-1 -> -0.42784129 | Q42: =Q29/$P$18-1 -> -0.38086025
D43: =D42+0.005 -> 0.088316088 | E43: =E30-$P$16 -> 478608.39 | F43: =F30-$P$16 -> 502459.67 | G43: =G30-$P$16 -> 530400.95 | H43: =H30-$P$16 -> 563582.92 | I43: =I30-$P$16 -> 603632.58 | L43: =D43 -> 0.088316088 | M43: =M30/$P$18-1 -> -0.56338718 | N43: =N30/$P$18-1 -> -0.54162873 | O43: =O30/$P$18-1 -> -0.51613915 | P43: =P30/$P$18-1 -> -0.48586874 | Q43: =Q30/$P$18-1 -> -0.44933325
C47: Dashboard: Terminal Multiple Method
M49: All figures in USD millions unless stated
E52: Main Outputs | M52: Selected Inputs
G54: Enterprise | H54: Equity | I54: Equity
E55: Live (Current Switch) | G55: Value | H55: Value | I55: Per Share | M55: Terminal EBITDA Multiple | P55: =Inputs!$G$143 -> 12
G56: =Model!$I$349 -> 589784.74 | H56: =G56-$P$57 -> 625467.74 | I56: =H56/$P$58 -> 176.4366 | M56: WACC | P56: =Inputs!$M$122 -> 0.078316088
E57: Best Case | F57: 1 | G57: 1252716.2 | H57: =G57-$P$57 -> 1288399.2 | I57: =H57/$P$58 -> 363.44124 | M57: Net Debt / (Net Cash) | O57: (End of 2025) | P57: =Inputs!$M$132 -> -35683
E58: Base Case | F58: 2 | G58: 589784.74 | H58: =G58-$P$57 -> 625467.74 | I58: =H58/$P$58 -> 176.4366 | M58: Shares Outstanding | O58: (FD, m) | P58: =Inputs!$G$140 -> 3545
E59: Worst Case | F59: 3 | G59: 223616.16 | H59: =G59-$P$57 -> 259299.16 | I59: =H59/$P$58 -> 73.145037 | M59: Current Share Price | O59: (US$/sh) | P59: =Inputs!$G$141 -> 309.22
E63: Enterprise Value | M63: Equity Value per Share
E65: Terminal EBITDA Multiple | M65: Terminal EBITDA Multiple
D66: =Model!$I$349 -> 589784.74 | E66: =F66-0.5 -> 11 | F66: =G66-0.5 -> 11.5 | G66: =Inputs!$G$143 -> 12 | H66: =G66+0.5 -> 12.5 | I66: =H66+0.5 -> 13 | M66: =E66 -> 11 | N66: =F66 -> 11.5 | O66: =G66 -> 12 | P66: =H66 -> 12.5 | Q66: =I66 -> 13
C67: WACC | D67: =D68-0.005 -> 0.068316088 | E67: 600258.26 | F67: 620279.05 | G67: 640299.83 | H67: 660320.62 | I67: 680341.41 | K67: WACC | L67: =D67 -> 0.068316088 | M67: =E80/$P$58 -> 179.39105 | N67: =F80/$P$58 -> 185.03866 | O67: =G80/$P$58 -> 190.68627 | P67: =H80/$P$58 -> 196.33388 | Q67: =I80/$P$58 -> 201.9815
D68: =D69-0.005 -> 0.073316088 | E68: 576146.78 | F68: 595298.88 | G68: 614450.98 | H68: 633603.08 | I68: 652755.17 | L68: =D68 -> 0.073316088 | M68: =E81/$P$58 -> 172.5895 | N68: =F81/$P$58 -> 177.99207 | O68: =G81/$P$58 -> 183.39463 | P68: =H81/$P$58 -> 188.7972 | Q68: =I81/$P$58 -> 194.19977
D69: =Inputs!$M$122 -> 0.078316088 | E69: 553134.98 | F69: 571459.86 | G69: 589784.74 | H69: 608109.62 | I69: 626434.5 | L69: =D69 -> 0.078316088 | M69: =E82/$P$58 -> 166.09816 | N69: =F82/$P$58 -> 171.26738 | O69: =G82/$P$58 -> 176.4366 | P69: =H82/$P$58 -> 181.60582 | Q69: =I82/$P$58 -> 186.77504
D70: =D69+0.005 -> 0.083316088 | E70: 531167.2 | F70: 548704.17 | G70: 566241.14 | H70: 583778.11 | I70: 601315.08 | L70: =D70 -> 0.083316088 | M70: =E83/$P$58 -> 159.90133 | N70: =F83/$P$58 -> 164.84828 | O70: =G83/$P$58 -> 169.79524 | P70: =H83/$P$58 -> 174.7422 | Q70: =I83/$P$58 -> 179.68916
D71: =D70+0.005 -> 0.088316088 | E71: 510190.83 | F71: 526977.17 | G71: 543763.5 | H71: 560549.84 | I71: 577336.18 | L71: =D71 -> 0.088316088 | M71: =E84/$P$58 -> 153.98415 | N71: =F84/$P$58 -> 158.71937 | O71: =G84/$P$58 -> 163.45458 | P71: =H84/$P$58 -> 168.1898 | Q71: =I84/$P$58 -> 172.92502
E76: Equity Value | M76: Premium / (Discount) to Share Price
E78: Terminal EBITDA Multiple | M78: Terminal EBITDA Multiple
E79: =E66 -> 11 | F79: =F66 -> 11.5 | G79: =G66 -> 12 | H79: =H66 -> 12.5 | I79: =I66 -> 13 | M79: =E79 -> 11 | N79: =F79 -> 11.5 | O79: =G79 -> 12 | P79: =H79 -> 12.5 | Q79: =I79 -> 13
C80: WACC | D80: =D81-0.005 -> 0.068316088 | E80: =E67-$P$57 -> 635941.26 | F80: =F67-$P$57 -> 655962.05 | G80: =G67-$P$57 -> 675982.83 | H80: =H67-$P$57 -> 696003.62 | I80: =I67-$P$57 -> 716024.41 | K80: WACC | L80: =D80 -> 0.068316088 | M80: =M67/$P$59-1 -> -0.4198595 | N80: =N67/$P$59-1 -> -0.40159544 | O80: =O67/$P$59-1 -> -0.38333138 | P80: =P67/$P$59-1 -> -0.36506732 | Q80: =Q67/$P$59-1 -> -0.34680326
D81: =D82-0.005 -> 0.073316088 | E81: =E68-$P$57 -> 611829.78 | F81: =F68-$P$57 -> 630981.88 | G81: =G68-$P$57 -> 650133.98 | H81: =H68-$P$57 -> 669286.08 | I81: =I68-$P$57 -> 688438.17 | L81: =D81 -> 0.073316088 | M81: =M68/$P$59-1 -> -0.44185531 | N81: =N68/$P$59-1 -> -0.42438372 | O81: =O68/$P$59-1 -> -0.40691212 | P81: =P68/$P$59-1 -> -0.38944053 | Q81: =Q68/$P$59-1 -> -0.37196893
D82: =D69 -> 0.078316088 | E82: =E69-$P$57 -> 588817.98 | F82: =F69-$P$57 -> 607142.86 | G82: =G69-$P$57 -> 625467.74 | H82: =H69-$P$57 -> 643792.62 | I82: =I69-$P$57 -> 662117.5 | L82: =D82 -> 0.078316088 | M82: =M69/$P$59-1 -> -0.46284793 | N82: =N69/$P$59-1 -> -0.44613097 | O82: =O69/$P$59-1 -> -0.42941401 | P82: =P69/$P$59-1 -> -0.41269705 | Q82: =Q69/$P$59-1 -> -0.39598009
D83: =D82+0.005 -> 0.083316088 | E83: =E70-$P$57 -> 566850.2 | F83: =F70-$P$57 -> 584387.17 | G83: =G70-$P$57 -> 601924.14 | H83: =H70-$P$57 -> 619461.11 | I83: =I70-$P$57 -> 636998.08 | L83: =D83 -> 0.083316088 | M83: =M70/$P$59-1 -> -0.48288815 | N83: =N70/$P$59-1 -> -0.46688997 | O83: =O70/$P$59-1 -> -0.45089178 | P83: =P70/$P$59-1 -> -0.43489359 | Q83: =Q70/$P$59-1 -> -0.4188954
D84: =D83+0.005 -> 0.088316088 | E84: =E71-$P$57 -> 545873.83 | F84: =F71-$P$57 -> 562660.17 | G84: =G71-$P$57 -> 579446.5 | H84: =H71-$P$57 -> 596232.84 | I84: =I71-$P$57 -> 613019.18 | L84: =D84 -> 0.088316088 | M84: =M71/$P$59-1 -> -0.50202395 | N84: =N71/$P$59-1 -> -0.48671053 | O84: =O71/$P$59-1 -> -0.47139711 | P84: =P71/$P$59-1 -> -0.45608369 | Q84: =Q71/$P$59-1 -> -0.44077028

Sheet Inputs
C1: AMIR J
C7: Scenario Drivers
C9: All figures in USD millions unless stated
C11: Driver switch | E11: =Outputs!G8 -> 2
G13: Forecast | H13: 2026 | I13: 2027 | J13: 2028 | K13: 2029 | L13: 2030 | M13: 2031 | N13: 2032 | O13: 2033 | P13: 2034 | Q13: 2035 | R13: Term
C16: Vehicle Deliveries Growth | H16: =INDEX(H17:H19,$E$11) -> 0.13 | I16: =INDEX(I17:I19,$E$11) -> 0.1 | J16: =INDEX(J17:J19,$E$11) -> 0.09 | K16: =INDEX(K17:K19,$E$11) -> 0.08 | L16: =INDEX(L17:L19,$E$11) -> 0.07 | M16: =INDEX(M17:M19,$E$11) -> 0.06 | N16: =INDEX(N17:N19,$E$11) -> 0.055 | O16: =INDEX(O17:O19,$E$11) -> 0.05 | ... R16: =INDEX(R17:R19,$E$11) -> 0.03
C17: Best Case | H17: 0.16 | I17: 0.14 | J17: 0.13 | K17: 0.12 | L17: 0.11 | M17: 0.09 | N17: 0.08 | O17: 0.07 | P17: 0.06 | Q17: 0.05 | R17: 0.035
C18: Base Case | H18: 0.13 | I18: 0.1 | J18: 0.09 | K18: 0.08 | L18: 0.07 | M18: 0.06 | N18: 0.055 | O18: 0.05 | P18: 0.04 | Q18: 0.035 | R18: 0.03
C19: Worst Case | H19: 0.09 | I19: 0.05 | J19: 0.04 | K19: 0.035 | L19: 0.03 | M19: 0.03 | N19: 0.025 | O19: 0.02 | P19: 0.02 | Q19: 0.02 | R19: 0.02
C22: Average Selling Price Change | H22: =INDEX(H23:H25,$E$11) -> -0.02 | I22: =INDEX(I23:I25,$E$11) -> -0.015 | J22: =INDEX(J23:J25,$E$11) -> -0.01 | K22: =INDEX(K23:K25,$E$11) -> -0.005 | L22: =INDEX(L23:L25,$E$11) -> 0 | M22: =INDEX(M23:M25,$E$11) -> 0.005 | N22: =INDEX(N23:N25,$E$11) -> 0.005 | O22: =INDEX(O23:O25,$E$11) -> 0.01 | ... R22: =INDEX(R23:R25,$E$11) -> 0.01
C23: Best Case | H23: -0.01 | I23: 0 | J23: 0.005 | K23: 0.01 | L23: 0.01 | M23: 0.01 | N23: 0.01 | O23: 0.015 | P23: 0.015 | Q23: 0.015 | R23: 0.015
C24: Base Case | H24: -0.02 | I24: -0.015 | J24: -0.01 | K24: -0.005 | L24: 0 | M24: 0.005 | N24: 0.005 | O24: 0.01 | P24: 0.01 | Q24: 0.01 | R24: 0.01
C25: Worst Case | H25: -0.04 | I25: -0.03 | J25: -0.02 | K25: -0.015 | L25: -0.01 | M25: -0.005 | N25: 0 | O25: 0 | P25: 0.005 | Q25: 0.005 | R25: 0.005
C28: Energy Revenue Growth | H28: =INDEX(H29:H31,$E$11) -> 0.18 | I28: =INDEX(I29:I31,$E$11) -> 0.33 | J28: =INDEX(J29:J31,$E$11) -> 0.22 | K28: =INDEX(K29:K31,$E$11) -> 0.18 | L28: =INDEX(L29:L31,$E$11) -> 0.15 | M28: =INDEX(M29:M31,$E$11) -> 0.13 | N28: =INDEX(N29:N31,$E$11) -> 0.11 | O28: =INDEX(O29:O31,$E$11) -> 0.09 | ... R28: =INDEX(R29:R31,$E$11) -> 0.05
C29: Best Case | H29: 0.29 | I29: 0.4 | J29: 0.31 | K29: 0.23 | L29: 0.2 | M29: 0.17 | N29: 0.14 | O29: 0.12 | P29: 0.1 | Q29: 0.08 | R29: 0.06
C30: Base Case | H30: 0.18 | I30: 0.33 | J30: 0.22 | K30: 0.18 | L30: 0.15 | M30: 0.13 | N30: 0.11 | O30: 0.09 | P30: 0.07 | Q30: 0.06 | R30: 0.05
C31: Worst Case | H31: 0.15 | I31: 0.16 | J31: 0.13 | K31: 0.1 | L31: 0.08 | M31: 0.07 | N31: 0.06 | O31: 0.05 | P31: 0.04 | Q31: 0.04 | R31: 0.035
C34: Services & Software Revenue Growth | H34: =INDEX(H35:H37,$E$11) -> 0.3 | I34: =INDEX(I35:I37,$E$11) -> 0.19 | J34: =INDEX(J35:J37,$E$11) -> 0.3 | K34: =INDEX(K35:K37,$E$11) -> 0.28 | L34: =INDEX(L35:L37,$E$11) -> 0.25 | M34: =INDEX(M35:M37,$E$11) -> 0.2 | N34: =INDEX(N35:N37,$E$11) -> 0.16 | O34: =INDEX(O35:O37,$E$11) -> 0.13 | ... R34: =INDEX(R35:R37,$E$11) -> 0.05
C35: Best Case | H35: 0.35 | I35: 0.28 | J35: 0.42 | K35: 0.38 | L35: 0.33 | M35: 0.27 | N35: 0.22 | O35: 0.18 | P35: 0.14 | Q35: 0.11 | R35: 0.06
C36: Base Case | H36: 0.3 | I36: 0.19 | J36: 0.3 | K36: 0.28 | L36: 0.25 | M36: 0.2 | N36: 0.16 | O36: 0.13 | P36: 0.1 | Q36: 0.08 | R36: 0.05
C37: Worst Case | H37: 0.16 | I37: 0.15 | J37: 0.14 | K37: 0.12 | L37: 0.1 | M37: 0.09 | N37: 0.08 | O37: 0.07 | P37: 0.06 | Q37: 0.05 | R37: 0.04
C40: Automotive Gross Margin (excl. D&A) | H40: =INDEX(H41:H43,$E$11) -> 0.18 | I40: =INDEX(I41:I43,$E$11) -> 0.19 | J40: =INDEX(J41:J43,$E$11) -> 0.25 | K40: =INDEX(K41:K43,$E$11) -> 0.255 | L40: =INDEX(L41:L43,$E$11) -> 0.26 | M40: =INDEX(M41:M43,$E$11) -> 0.265 | N40: =INDEX(N41:N43,$E$11) -> 0.27 | O40: =INDEX(O41:O43,$E$11) -> 0.27 | ... R40: =INDEX(R41:R43,$E$11) -> 0.275
C41: Best Case | H41: 0.23 | I41: 0.265 | J41: 0.275 | K41: 0.285 | L41: 0.29 | M41: 0.295 | N41: 0.3 | O41: 0.3 | P41: 0.305 | Q41: 0.305 | R41: 0.305
C42: Base Case | H42: 0.18 | I42: 0.19 | J42: 0.25 | K42: 0.255 | L42: 0.26 | M42: 0.265 | N42: 0.27 | O42: 0.27 | P42: 0.275 | Q42: 0.275 | R42: 0.275
C43: Worst Case | H43: 0.15 | I43: 0.17 | J43: 0.225 | K43: 0.23 | L43: 0.235 | M43: 0.24 | N43: 0.24 | O43: 0.245 | P43: 0.245 | Q43: 0.245 | R43: 0.245
C46: Energy Gross Margin (excl. D&A) | H46: =INDEX(H47:H49,$E$11) -> 0.29 | I46: =INDEX(I47:I49,$E$11) -> 0.29 | J46: =INDEX(J47:J49,$E$11) -> 0.34 | K46: =INDEX(K47:K49,$E$11) -> 0.35 | L46: =INDEX(L47:L49,$E$11) -> 0.35 | M46: =INDEX(M47:M49,$E$11) -> 0.35 | N46: =INDEX(N47:N49,$E$11) -> 0.35 | O46: =INDEX(O47:O49,$E$11) -> 0.35 | ... R46: =INDEX(R47:R49,$E$11) -> 0.35
C47: Best Case | H47: 0.35 | I47: 0.36 | J47: 0.37 | K47: 0.38 | L47: 0.38 | M47: 0.38 | N47: 0.38 | O47: 0.38 | P47: 0.38 | Q47: 0.38 | R47: 0.38
C48: Base Case | H48: 0.29 | I48: 0.29 | J48: 0.34 | K48: 0.35 | L48: 0.35 | M48: 0.35 | N48: 0.35 | O48: 0.35 | P48: 0.35 | Q48: 0.35 | R48: 0.35
C49: Worst Case | H49: 0.26 | I49: 0.25 | J49: 0.3 | K49: 0.3 | L49: 0.3 | M49: 0.3 | N49: 0.3 | O49: 0.3 | P49: 0.3 | Q49: 0.3 | R49: 0.3
C52: Services & Software Gross Margin (excl. D&A) | H52: =INDEX(H53:H55,$E$11) -> 0.12 | I52: =INDEX(I53:I55,$E$11) -> 0.12 | J52: =INDEX(J53:J55,$E$11) -> 0.26 | K52: =INDEX(K53:K55,$E$11) -> 0.31 | L52: =INDEX(L53:L55,$E$11) -> 0.35 | M52: =INDEX(M53:M55,$E$11) -> 0.38 | N52: =INDEX(N53:N55,$E$11) -> 0.4 | O52: =INDEX(O53:O55,$E$11) -> 0.41 | ... R52: =INDEX(R53:R55,$E$11) -> 0.42
C53: Best Case | H53: 0.16 | I53: 0.23 | J53: 0.34 | K53: 0.4 | L53: 0.45 | M53: 0.48 | N53: 0.5 | O53: 0.51 | P53: 0.52 | Q53: 0.52 | R53: 0.52
C54: Base Case | H54: 0.12 | I54: 0.12 | J54: 0.26 | K54: 0.31 | L54: 0.35 | M54: 0.38 | N54: 0.4 | O54: 0.41 | P54: 0.42 | Q54: 0.42 | R54: 0.42
C55: Worst Case | H55: 0.1 | I55: 0.1 | J55: 0.18 | K55: 0.21 | L55: 0.23 | M55: 0.25 | N55: 0.26 | O55: 0.27 | P55: 0.28 | Q55: 0.28 | R55: 0.28
C58: Operating Expense Growth (excl. D&A) | H58: =INDEX(H59:H61,$E$11) -> 0.22 | I58: =INDEX(I59:I61,$E$11) -> 0.15 | J58: =INDEX(J59:J61,$E$11) -> 0.12 | K58: =INDEX(K59:K61,$E$11) -> 0.1 | L58: =INDEX(L59:L61,$E$11) -> 0.08 | M58: =INDEX(M59:M61,$E$11) -> 0.07 | N58: =INDEX(N59:N61,$E$11) -> 0.06 | O58: =INDEX(O59:O61,$E$11) -> 0.06 | ... R58: =INDEX(R59:R61,$E$11) -> 0.04
C59: Best Case | H59: 0.18 | I59: 0.12 | J59: 0.1 | K59: 0.08 | L59: 0.07 | M59: 0.06 | N59: 0.05 | O59: 0.05 | P59: 0.045 | Q59: 0.045 | R59: 0.035
C60: Base Case | H60: 0.22 | I60: 0.15 | J60: 0.12 | K60: 0.1 | L60: 0.08 | M60: 0.07 | N60: 0.06 | O60: 0.06 | P60: 0.05 | Q60: 0.05 | R60: 0.04
C61: Worst Case | H61: 0.2 | I61: 0.12 | J61: 0.08 | K61: 0.06 | L61: 0.05 | M61: 0.04 | N61: 0.04 | O61: 0.035 | P61: 0.03 | Q61: 0.03 | R61: 0.025
C64: Capital Expenditure | H64: =INDEX(H65:H67,$E$11) -> 24000 | I64: =INDEX(I65:I67,$E$11) -> 17000 | J64: =INDEX(J65:J67,$E$11) -> 15000 | K64: =INDEX(K65:K67,$E$11) -> 14000 | L64: =INDEX(L65:L67,$E$11) -> 13500 | M64: =INDEX(M65:M67,$E$11) -> 13500 | N64: =INDEX(N65:N67,$E$11) -> 14000 | O64: =INDEX(O65:O67,$E$11) -> 14500 | ... R64: =INDEX(R65:R67,$E$11) -> 15269.75
C65: Best Case | H65: 20000 | I65: 16000 | J65: 14000 | K65: 13000 | L65: 12500 | M65: 12500 | N65: 13000 | O65: 13500 | P65: 14000 | Q65: 14500 | R65: =Model!$T$121 -> 15269.75
C66: Base Case | H66: 24000 | I66: 17000 | J66: 15000 | K66: 14000 | L66: 13500 | M66: 13500 | N66: 14000 | O66: 14500 | P66: 15000 | Q66: 15500 | R66: =Model!$T$121 -> 15269.75
C67: Worst Case | H67: 29000 | I67: 17500 | J67: 14000 | K67: 11000 | L67: 9500 | M67: 9000 | N67: 9000 | O67: 9500 | P67: 10000 | Q67: 10500 | R67: =Model!$T$121 -> 15269.75
T69: Terminal capital expenditure is set equal to terminal depreciation, consistent with a steady state.
C71: Working Capital Assumptions
C73: Accounts Receivable | F73: (Days) | H73: 18 | I73: 18 | J73: 18 | K73: 18 | L73: 18 | M73: 18 | N73: 18 | O73: 18 | P73: 18 | Q73: 18 | R73: =Q73 -> 18
C74: Inventory | F74: (Days) | H74: 58 | I74: 58 | J74: 58 | K74: 58 | L74: 58 | M74: 58 | N74: 58 | O74: 58 | P74: 58 | Q74: 58 | R74: =Q74 -> 58
C75: Accounts Payable | F75: (Days) | H75: 62 | I75: 62 | J75: 62 | K75: 62 | L75: 62 | M75: 62 | N75: 62 | O75: 62 | P75: 62 | Q75: 62 | R75: =Q75 -> 62
T77: Days held at FY2025 reported levels (DSO 17, DPO 61). Terminal year equals the final forecast year.
T78: Source: Tesla Q4 and FY2025 Update, Balance Sheet, ir.tesla.com.
C81: Weighted Average Cost of Capital
C83: All figures in USD millions unless stated.
C85: Peer Company | E85: Region | G85: Debt | H85: Equity | I85: Tax Rate | J85: Debt/Equity | K85: Debt/Capital | L85: Levered Beta | M85: Unlevered Beta
C87: BYD Company Ltd. | E87: China | G87: 28480 | H87: 38700 | I87: 0.21 | J87: =G87/H87 -> 0.73591731 | K87: =G87/(G87+H87) -> 0.4239357 | L87: 1.1 | M87: =L87/(1+(1-I87)*J87) -> 0.69559733
C88: Li Auto Inc. | E88: China | G88: 2660 | H88: 10350 | I88: 0.21 | J88: =G88/H88 -> 0.25700483 | K88: =G88/(G88+H88) -> 0.20445811 | L88: 1.35 | M88: =L88/(1+(1-I88)*J88) -> 1.122163
C89: XPeng Inc. | E89: China | G89: 3720 | H89: 4149 | I89: 0.21 | J89: =G89/H89 -> 0.89660159 | K89: =G89/(G89+H89) -> 0.47274114 | L89: 2 | M89: =L89/(1+(1-I89)*J89) -> 1.1707441
C90: NIO Inc. | E90: China | G90: 3930 | H90: 2140 | I90: 0.21 | J90: =G90/H90 -> 1.8364486 | K90: =G90/(G90+H90) -> 0.64744646 | L90: 1.7 | M90: =L90/(1+(1-I90)*J90) -> 0.69365264
C91: Rivian Automotive Inc. | E91: US | G91: 5100 | H91: 4590 | I91: 0.21 | J91: =G91/H91 -> 1.1111111 | K91: =G91/(G91+H91) -> 0.52631579 | L91: 2 | M91: =L91/(1+(1-I91)*J91) -> 1.0650888
C92: Lucid Group Inc. | E92: US | G92: 3170 | H92: 2040 | I92: 0.21 | J92: =G92/H92 -> 1.5539216 | K92: =G92/(G92+H92) -> 0.6084453 | L92: 1.95 | M92: =L92/(1+(1-I92)*J92) -> 0.87538235
C93: General Motors Co. | E93: US | G93: 127700 | H93: 63640 | I93: 0.21 | J93: =G93/H93 -> 2.0065996 | K93: =G93/(G93+H93) -> 0.66739835 | L93: 1.45 | M93: =L93/(1+(1-I93)*J93) -> 0.56088207
C94: Ford Motor Co. | E94: US | G94: 163300 | H94: 35760 | I94: 0.21 | J94: =G94/H94 -> 4.5665548 | K94: =G94/(G94+H94) -> 0.82035567 | L94: 1.55 | M94: =L94/(1+(1-I94)*J94) -> 0.33640231
H96: Average | I96: =AVERAGE(I87:I94) -> 0.21 | J96: =AVERAGE(J87:J94) -> 1.6205199 | K96: =AVERAGE(K87:K94) -> 0.54638706 | L96: =AVERAGE(L87:L94) -> 1.6375 | M96: =AVERAGE(M87:M94) -> 0.81498906
H97: Median | I97: =MEDIAN(I87:I94) -> 0.21 | J97: =MEDIAN(J87:J94) -> 1.3325163 | K97: =MEDIAN(K87:K94) -> 0.56738054 | L97: =MEDIAN(L87:L94) -> 1.625 | M97: =MEDIAN(M87:M94) -> 0.78548984
C100: Risk Premium for Equity | I100: Cost of Equity
C102: Market Risk Premium | G102: 0.045 | I102: Risk Free Rate (US 10Y) | M102: 0.042
C103: Average Unlevered Beta | G103: =M96 -> 0.81498906 | I103: Equity Risk Premium | M103: =G105 -> 0.038180093
C104: Re-levered Beta | G104: =G103*(1+(1-M112)*G115) -> 0.84844651 | I104: Company Specific Premium | M104: 0
C105: Equity Risk Premium | G105: =G102*G104 -> 0.038180093 | I105: Cost of Equity | M105: =SUM(M102:M104) -> 0.080180093
C109: Capital Structure | I109: Cost of Debt
F110: Current | G110: Target
C111: Total Debt | E111: 16080 | F111: =E111/$E$113 -> 0.014456988 | G111: 0.05 | I111: Pre-Tax Cost of Debt | M111: 0.055
C112: Market Capitalisation | E112: =G140*G141 -> 1096184.9 | F112: =E112/$E$113 -> 0.98554301 | G112: =1-G111 -> 0.95 | I112: Marginal Tax Rate | M112: 0.22
C113: Total | E113: =SUM(E111:E112) -> 1112264.9 | F113: =SUM(F111:F112) -> 1 | G113: =SUM(G111:G112) -> 1 | I113: After-Tax Cost of Debt | M113: =M111*(1-M112) -> 0.0429
C115: Debt / Equity | F115: =F111/F112 -> 0.014669058 | G115: =G111/G112 -> 0.052631579 | I115: Weighted Average Cost of Capital
C117: Unlevered Beta = Levered Beta / (1 + (1 - Tax Rate) x Debt-to-Equity). | L117: Weight | M117: Cost
C118: Re-levered Beta = Average Unlevered Beta (peer mean, M96) x (1 + (1 - Tax Rate) x Target Debt-to-Equity). | I118: Debt Capital | L118: =G111 -> 0.05 | M118: =M113 -> 0.0429
C119: Peer debt excludes captive finance obligations at GM, Ford and Toyota. Betas are 5-year monthly. | I119: Equity Capital | L119: =G112 -> 0.95 | M119: =M105 -> 0.080180093
I122: Weighted Average Cost of Capital | M122: =SUMPRODUCT(L118:L119,M118:M119) -> 0.078316088
C126: Other Inputs
C127: All figures in USD millions unless stated.
C129: Dates | I129: End of FY2025 Balances
C130: Valuation Date | F130: (YYYY-MM-DD) | G130: 46203 | I130: Cash, Cash Equivalents and Investments | M130: 44059
C131: First Expected Cash Flow | F131: (YYYY-MM-DD) | G131: 46387 | I131: Total Debt and Finance Leases | M131: 8376
C132: First Fiscal Year End for Forecast | F132: (YYYY-MM-DD) | G132: 46387 | I132: Net Debt / (Net Cash) | M132: =M131-M130 -> -35683
C133: First Year of Forecast | F133: (YYYY) | G133: =YEAR(G132) -> 2026 | I133: PP&E and Energy Storage Systems, Net | M133: 45247
C134: Incorrect Date Set for Valuation? | G134: =IF(G130>G131,1,0) -> 0 | I134: Tax Basis for PP&E | M134: 34000
C135: Incorrect Date Set for First Cash Flow? | G135: =IF(G131>G132,1,0) -> 0 | I135: Tax Losses Carried Forward | M135: 0
C136: Days in Period | G136: 365
I138: Operating and Tax Inputs
C139: Valuation | I139: Projected Interest Expense | M139: 350
C140: Shares Outstanding | F140: (FD, millions) | G140: 3545 | I140: First Year Tax Depreciation | M140: 0.5
C141: Current Share Price | F141: (US$/sh) | G141: 309.22 | I141: Blended Tax Depreciation Rate | M141: 0.2
C142: Terminal Growth Rate | G142: 0.03 | I142: First Year Accounting Depreciation | M142: 0.5
C143: Terminal EBITDA Multiple | G143: 12 | I143: Useful Life: Existing Assets | L143: (Years) | M143: 8
C144: Weighted Average Cost of Capital (WACC) | G144: =M122 -> 0.078316088 | I144: Useful Life: New Assets | L144: (Years) | M144: 10
C145: Terminal Growth Greater Than or Equal To WACC? | G145: =IF(G142>=G144,1,0) -> 0
I147: Balances per Tesla Q4 and FY2025 Update, Balance Sheet (31-Dec-2025), ir.tesla.com.
I148: Useful lives implied by FY2025 D&A of $6,148m on a $45,247m asset base.
I149: Tesla has no material remaining US federal loss carryforwards; opening tax losses set to nil.
I150: Share count is FY2025 diluted weighted average per Tesla Q4-2025 (3,539m), rounded to 3,545m.
I151: Share price is the last close prior to the valuation cut-off used in this analysis.

Sheet Model
C1: AMIR J
C8: Revenue Schedule
C10: All figures in USD millions unless stated | G10: 2023 | H10: 2024 | I10: 2025 | J10: =Inputs!H$13 -> 2026 | K10: =Inputs!I$13 -> 2027 | L10: =Inputs!J$13 -> 2028 | M10: =Inputs!K$13 -> 2029 | N10: =Inputs!L$13 -> 2030 | O10: =Inputs!M$13 -> 2031 | P10: =Inputs!N$13 -> 2032 | Q10: =Inputs!O$13 -> 2033 | ... S10: =Inputs!Q$13 -> 2035 | T10: Term
C11: =IF(Inputs!$E$11=1,"Best Case Selected",IF(Inputs!$E$11=2,"Base Case Selected","Worst Case Selected")) -> Base Case Selected
C13: Vehicle Deliveries Growth | H13: =H14/G14-1 -> -0.01070176 | I13: =I14/H14-1 -> -0.085566049 | J13: =Inputs!H16 -> 0.13 | K13: =Inputs!I16 -> 0.1 | L13: =Inputs!J16 -> 0.09 | M13: =Inputs!K16 -> 0.08 | N13: =Inputs!L16 -> 0.07 | O13: =Inputs!M16 -> 0.06 | P13: =Inputs!N16 -> 0.055 | Q13: =Inputs!O16 -> 0.05 | ... T13: =Inputs!R16 -> 0.03
C14: Vehicle Deliveries | E14: (Units) | G14: 1808581 | H14: 1789226 | I14: 1636129 | J14: =I14*(1+J13) -> 1848825.8 | K14: =J14*(1+K13) -> 2033708.3 | L14: =K14*(1+L13) -> 2216742.1 | M14: =L14*(1+M13) -> 2394081.5 | N14: =M14*(1+N13) -> 2561667.2 | O14: =N14*(1+O13) -> 2715367.2 | P14: =O14*(1+P13) -> 2864712.4 | Q14: =P14*(1+Q13) -> 3007948 | ... T14: =S14*(1+T13) -> 3334887.9
C16: Average Selling Price Change | H16: =H17/G17-1 -> -0.054784615 | I16: =I17/H17-1 -> -0.013471711 | J16: =Inputs!H22 -> -0.02 | K16: =Inputs!I22 -> -0.015 | L16: =Inputs!J22 -> -0.01 | M16: =Inputs!K22 -> -0.005 | N16: =Inputs!L22 -> 0 | O16: =Inputs!M22 -> 0.005 | P16: =Inputs!N22 -> 0.005 | Q16: =Inputs!O22 -> 0.01 | ... T16: =Inputs!R22 -> 0.01
C17: Average Selling Price | E17: (USD/Unit) | G17: =G19*1000000/G14 -> 45571.086 | H17: =H19*1000000/H14 -> 43074.491 | I17: =I19*1000000/I14 -> 42494.204 | J17: =I17*(1+J16) -> 41644.32 | K17: =J17*(1+K16) -> 41019.655 | L17: =K17*(1+L16) -> 40609.459 | M17: =L17*(1+M16) -> 40406.412 | N17: =M17*(1+N16) -> 40406.412 | O17: =N17*(1+O16) -> 40608.444 | P17: =O17*(1+P16) -> 40811.486 | Q17: =P17*(1+Q16) -> 41219.601 | ... T17: =S17*(1+T16) -> 42468.596
C19: Automotive Revenue | G19: 82419 | H19: 77070 | I19: 69526 | J19: =J14*J17/1000000 -> 76993.092 | K19: =K14*K17/1000000 -> 83422.016 | L19: =L14*L17/1000000 -> 90020.697 | M19: =M14*M17/1000000 -> 96736.241 | N19: =N14*N17/1000000 -> 103507.78 | O19: =O14*O17/1000000 -> 110266.84 | P19: =P14*P17/1000000 -> 116913.17 | Q19: =Q14*Q17/1000000 -> 123986.42 | ... T19: =T14*T17/1000000 -> 141628.01
C21: Energy Revenue Growth | H21: =H22/G22-1 -> 0.67125104 | I21: =I22/H22-1 -> 0.26621059 | J21: =Inputs!H28 -> 0.18 | K21: =Inputs!I28 -> 0.33 | L21: =Inputs!J28 -> 0.22 | M21: =Inputs!K28 -> 0.18 | N21: =Inputs!L28 -> 0.15 | O21: =Inputs!M28 -> 0.13 | P21: =Inputs!N28 -> 0.11 | Q21: =Inputs!O28 -> 0.09 | ... T21: =Inputs!R28 -> 0.05
C22: Energy Generation and Storage Revenue | G22: 6035 | H22: 10086 | I22: 12771 | J22: =I22*(1+J21) -> 15069.78 | K22: =J22*(1+K21) -> 20042.807 | L22: =K22*(1+L21) -> 24452.225 | M22: =L22*(1+M21) -> 28853.626 | N22: =M22*(1+N21) -> 33181.669 | O22: =N22*(1+O21) -> 37495.286 | P22: =O22*(1+P21) -> 41619.768 | Q22: =P22*(1+Q21) -> 45365.547 | ... T22: =S22*(1+T21) -> 54026.284
C24: Services and Software Revenue Growth | H24: =H25/G25-1 -> 0.26625796 | I24: =I25/H25-1 -> 0.18948168 | J24: =Inputs!H34 -> 0.3 | K24: =Inputs!I34 -> 0.19 | L24: =Inputs!J34 -> 0.3 | M24: =Inputs!K34 -> 0.28 | N24: =Inputs!L34 -> 0.25 | O24: =Inputs!M34 -> 0.2 | P24: =Inputs!N34 -> 0.16 | Q24: =Inputs!O34 -> 0.13 | ... T24: =Inputs!R34 -> 0.05
C25: Services, Software and Other Revenue | G25: 8319 | H25: 10534 | I25: 12530 | J25: =I25*(1+J24) -> 16289 | K25: =J25*(1+K24) -> 19383.91 | L25: =K25*(1+L24) -> 25199.083 | M25: =L25*(1+M24) -> 32254.826 | N25: =M25*(1+N24) -> 40318.533 | O25: =N25*(1+O24) -> 48382.239 | P25: =O25*(1+P24) -> 56123.398 | Q25: =P25*(1+Q24) -> 63419.439 | ... T25: =S25*(1+T24) -> 79109.409
C27: Total Revenue | G27: =G19+G22+G25 -> 96773 | H27: =H19+H22+H25 -> 97690 | I27: =I19+I22+I25 -> 94827 | J27: =J19+J22+J25 -> 108351.87 | K27: =K19+K22+K25 -> 122848.73 | L27: =L19+L22+L25 -> 139672.01 | M27: =M19+M22+M25 -> 157844.69 | N27: =N19+N22+N25 -> 177007.98 | ... T27: =T19+T22+T25 -> 274763.7
C28: Revenue Growth | H28: =H27/G27-1 -> 0.0094757835 | I28: =I27/H27-1 -> -0.029306992 | J28: =J27/I27-1 -> 0.14262681 | K28: =K27/J27-1 -> 0.13379428 | L28: =L27/K27-1 -> 0.13694298 | M28: =M27/L27-1 -> 0.13010974 | N28: =N27/M27-1 -> 0.12140597 | O28: =O27/N27-1 -> 0.10811028 | ... T28: =T27/S27-1 -> 0.044977616
C30: Memo: Automotive % of Revenue | G30: =G19/G27 -> 0.8516735 | H30: =H19/H27 -> 0.78892415 | I30: =I19/I27 -> 0.73318781 | J30: =J19/J27 -> 0.71058387 | K30: =K19/K27 -> 0.67906289 | L30: =L19/L27 -> 0.64451496 | M30: =M19/M27 -> 0.6128571 | N30: =N19/N27 -> 0.58476334 | ... T30: =T19/T27 -> 0.51545385
C31: Memo: Energy % of Revenue | G31: =G22/G27 -> 0.062362436 | H31: =H22/H27 -> 0.10324496 | I31: =I22/I27 -> 0.13467683 | J31: =J22/J27 -> 0.13908186 | K31: =K22/K27 -> 0.1631503 | L31: =L22/L27 -> 0.17506891 | M31: =M22/M27 -> 0.18279757 | N31: =N22/N27 -> 0.18745861 | ... T31: =T22/T27 -> 0.19662817
C32: Memo: Services and Software % of Revenue | G32: =G25/G27 -> 0.08596406 | H32: =H25/H27 -> 0.10783089 | I32: =I25/I27 -> 0.13213536 | J32: =J25/J27 -> 0.15033427 | K32: =K25/K27 -> 0.15778681 | L32: =L25/L27 -> 0.18041613 | M32: =M25/M27 -> 0.20434533 | N32: =N25/N27 -> 0.22777805 | ... T32: =T25/T27 -> 0.28791798
C34: FY2023-FY2025 actuals per Tesla Q4 and FY2025 Update, Financial Summary, ir.tesla.com.
C36: Cost and Gross Profit Schedule
C38: All figures in USD millions unless stated | G38: 2023 | H38: 2024 | I38: 2025 | J38: =Inputs!H$13 -> 2026 | K38: =Inputs!I$13 -> 2027 | L38: =Inputs!J$13 -> 2028 | M38: =Inputs!K$13 -> 2029 | N38: =Inputs!L$13 -> 2030 | O38: =Inputs!M$13 -> 2031 | P38: =Inputs!N$13 -> 2032 | Q38: =Inputs!O$13 -> 2033 | ... S38: =Inputs!Q$13 -> 2035 | T38: Term
C39: =IF(Inputs!$E$11=1,"Best Case Selected",IF(Inputs!$E$11=2,"Base Case Selected","Worst Case Selected")) -> Base Case Selected
C41: Automotive Gross Margin (excl. D&A) | G41: =1-G42/G19 -> 0.19449399 | H41: =1-H42/H19 -> 0.18420916 | I41: =1-I42/I19 -> 0.1777896 | J41: =Inputs!H40 -> 0.18 | K41: =Inputs!I40 -> 0.19 | L41: =Inputs!J40 -> 0.25 | M41: =Inputs!K40 -> 0.255 | N41: =Inputs!L40 -> 0.26 | O41: =Inputs!M40 -> 0.265 | P41: =Inputs!N40 -> 0.27 | Q41: =Inputs!O40 -> 0.27 | ... T41: =Inputs!R40 -> 0.275
C42: Automotive Cost of Revenues (excl. D&A) | G42: 66389 | H42: 62873 | I42: 57165 | J42: =J19*(1-J41) -> 63134.336 | K42: =K19*(1-K41) -> 67571.833 | L42: =L19*(1-L41) -> 67515.523 | M42: =M19*(1-M41) -> 72068.5 | N42: =N19*(1-N41) -> 76595.756 | O42: =O19*(1-O41) -> 81046.124 | P42: =P19*(1-P41) -> 85346.614 | Q42: =Q19*(1-Q41) -> 90510.084 | ... T42: =T19*(1-T41) -> 102680.3
C43: Automotive Gross Profit (excl. D&A) | G43: =G19-G42 -> 16030 | H43: =H19-H42 -> 14197 | I43: =I19-I42 -> 12361 | J43: =J19-J42 -> 13858.757 | K43: =K19-K42 -> 15850.183 | L43: =L19-L42 -> 22505.174 | M43: =M19-M42 -> 24667.741 | N43: =N19-N42 -> 26912.022 | ... T43: =T19-T42 -> 38947.702
C45: Energy Generation and Storage Gross Margin (excl. D&A) | G45: =1-G46/G22 -> 0.18906379 | H45: =1-H46/H22 -> 0.26174896 | I45: =1-I46/I22 -> 0.29770574 | J45: =Inputs!H46 -> 0.29 | K45: =Inputs!I46 -> 0.29 | L45: =Inputs!J46 -> 0.34 | M45: =Inputs!K46 -> 0.35 | N45: =Inputs!L46 -> 0.35 | O45: =Inputs!M46 -> 0.35 | P45: =Inputs!N46 -> 0.35 | Q45: =Inputs!O46 -> 0.35 | ... T45: =Inputs!R46 -> 0.35
C46: Energy Generation and Storage Cost of Revenues (excl. D&A) | G46: 4894 | H46: 7446 | I46: 8969 | J46: =J22*(1-J45) -> 10699.544 | K46: =K22*(1-K45) -> 14230.393 | L46: =L22*(1-L45) -> 16138.469 | M46: =M22*(1-M45) -> 18754.857 | N46: =N22*(1-N45) -> 21568.085 | O46: =O22*(1-O45) -> 24371.936 | P46: =P22*(1-P45) -> 27052.849 | Q46: =Q22*(1-Q45) -> 29487.606 | ... T46: =T22*(1-T45) -> 35117.084
C47: Energy Generation and Storage Gross Profit (excl. D&A) | G47: =G22-G46 -> 1141 | H47: =H22-H46 -> 2640 | I47: =I22-I46 -> 3802 | J47: =J22-J46 -> 4370.2362 | K47: =K22-K46 -> 5812.4141 | L47: =L22-L46 -> 8313.7565 | M47: =M22-M46 -> 10098.769 | N47: =N22-N46 -> 11613.584 | ... T47: =T22-T46 -> 18909.199
C49: Services and Software Gross Margin (excl. D&A) | G49: =1-G50/G25 -> 0.058781103 | H49: =1-H50/H25 -> 0.058192519 | I49: =1-I50/I25 -> 0.074301676 | J49: =Inputs!H52 -> 0.12 | K49: =Inputs!I52 -> 0.12 | L49: =Inputs!J52 -> 0.26 | M49: =Inputs!K52 -> 0.31 | N49: =Inputs!L52 -> 0.35 | O49: =Inputs!M52 -> 0.38 | P49: =Inputs!N52 -> 0.4 | Q49: =Inputs!O52 -> 0.41 | ... T49: =Inputs!R52 -> 0.42
C50: Services and Software Cost of Revenues (excl. D&A) | G50: 7830 | H50: 9921 | I50: 11599 | J50: =J25*(1-J49) -> 14334.32 | K50: =K25*(1-K49) -> 17057.841 | L50: =L25*(1-L49) -> 18647.321 | M50: =M25*(1-M49) -> 22255.83 | N50: =N25*(1-N49) -> 26207.046 | O50: =O25*(1-O49) -> 29996.988 | P50: =P25*(1-P49) -> 33674.039 | Q50: =Q25*(1-Q49) -> 37417.469 | ... T50: =T25*(1-T49) -> 45883.457
C51: Services and Software Gross Profit (excl. D&A) | G51: =G25-G50 -> 489 | H51: =H25-H50 -> 613 | I51: =I25-I50 -> 931 | J51: =J25-J50 -> 1954.68 | K51: =K25-K50 -> 2326.0692 | L51: =L25-L50 -> 6551.7616 | M51: =M25-M50 -> 9998.9961 | N51: =N25-N50 -> 14111.486 | ... T51: =T25-T50 -> 33225.952
C53: Total Cost of Revenues (excl. D&A) | G53: =G42+G46+G50 -> 79113 | H53: =H42+H46+H50 -> 80240 | I53: =I42+I46+I50 -> 77733 | J53: =J42+J46+J50 -> 88168.2 | K53: =K42+K46+K50 -> 98860.067 | L53: =L42+L46+L50 -> 102301.31 | M53: =M42+M46+M50 -> 113079.19 | N53: =N42+N46+N50 -> 124370.89 | ... T53: =T42+T46+T50 -> 183680.85
C54: Total Gross Profit (excl. D&A) | G54: =G27-G53 -> 17660 | H54: =H27-H53 -> 17450 | I54: =I27-I53 -> 17094 | J54: =J27-J53 -> 20183.673 | K54: =K27-K53 -> 23988.666 | L54: =L27-L53 -> 37370.692 | M54: =M27-M53 -> 44765.507 | N54: =N27-N53 -> 52637.093 | ... T54: =T27-T53 -> 91082.853
C55: Gross Margin (excl. D&A) | G55: =G54/G27 -> 0.18248892 | H55: =H54/H27 -> 0.17862627 | I55: =I54/I27 -> 0.18026511 | J55: =J54/J27 -> 0.18627895 | K55: =K54/K27 -> 0.19526995 | L55: =L54/L27 -> 0.26756036 | M55: =M54/M27 -> 0.28360476 | N55: =N54/N27 -> 0.2973713 | ... T55: =T54/T27 -> 0.33149522
C57: Depreciation and amortisation is presented separately below and has been reallocated out of cost of revenues.
C59: Income Statement
C61: All figures in USD millions unless stated | G61: 2023 | H61: 2024 | I61: 2025 | J61: =Inputs!H$13 -> 2026 | K61: =Inputs!I$13 -> 2027 | L61: =Inputs!J$13 -> 2028 | M61: =Inputs!K$13 -> 2029 | N61: =Inputs!L$13 -> 2030 | O61: =Inputs!M$13 -> 2031 | P61: =Inputs!N$13 -> 2032 | Q61: =Inputs!O$13 -> 2033 | ... S61: =Inputs!Q$13 -> 2035 | T61: Term
C62: =IF(Inputs!$E$11=1,"Best Case Selected",IF(Inputs!$E$11=2,"Base Case Selected","Worst Case Selected")) -> Base Case Selected
C64: Interest Expense | D64: =Inputs!$M$139 -> 350
C65: Marginal Tax Rate | D65: =Inputs!$M$112 -> 0.22
C67: Depreciation and Amortisation | G67: 4667 | H67: 5368 | I67: 6148 | J67: =J146 -> 6855.875 | K67: =K146 -> 8905.875 | L67: =L146 -> 10505.875 | M67: =M146 -> 11955.875 | N67: =N146 -> 13330.875 | O67: =O146 -> 14680.875 | P67: =P146 -> 16055.875 | Q67: =Q146 -> 17480.875 | ... T67: =T146 -> 15269.75
C69: Revenue | G69: =G27 -> 96773 | H69: =H27 -> 97690 | I69: =I27 -> 94827 | J69: =J27 -> 108351.87 | K69: =K27 -> 122848.73 | L69: =L27 -> 139672.01 | M69: =M27 -> 157844.69 | N69: =N27 -> 177007.98 | ... T69: =T27 -> 274763.7
C70: Cost of Revenues (excl. D&A) | G70: =G53 -> 79113 | H70: =H53 -> 80240 | I70: =I53 -> 77733 | J70: =J53 -> 88168.2 | K70: =K53 -> 98860.067 | L70: =L53 -> 102301.31 | M70: =M53 -> 113079.19 | N70: =N53 -> 124370.89 | ... T70: =T53 -> 183680.85
C71: Gross Profit (excl. D&A) | G71: =G69-G70 -> 17660 | H71: =H69-H70 -> 17450 | I71: =I69-I70 -> 17094 | J71: =J69-J70 -> 20183.673 | K71: =K69-K70 -> 23988.666 | L71: =L69-L70 -> 37370.692 | M71: =M69-M70 -> 44765.507 | N71: =N69-N70 -> 52637.093 | ... T71: =T69-T70 -> 91082.853
C73: Operating Expense Growth | H73: =H74/G74-1 -> 0.17219751 | I73: =I74/H74-1 -> 0.18464831 | J73: =Inputs!H58 -> 0.22 | K73: =Inputs!I58 -> 0.15 | L73: =Inputs!J58 -> 0.12 | M73: =Inputs!K58 -> 0.1 | N73: =Inputs!L58 -> 0.08 | O73: =Inputs!M58 -> 0.07 | P73: =Inputs!N58 -> 0.06 | Q73: =Inputs!O58 -> 0.06 | ... T73: =Inputs!R58 -> 0.04
C74: Operating Expenses (excl. D&A) | G74: 8769 | H74: 10279 | I74: 12177 | J74: =I74*(1+J73) -> 14855.94 | K74: =J74*(1+K73) -> 17084.331 | L74: =K74*(1+L73) -> 19134.451 | M74: =L74*(1+M73) -> 21047.896 | N74: =M74*(1+N73) -> 22731.727 | O74: =N74*(1+O73) -> 24322.948 | P74: =O74*(1+P73) -> 25782.325 | Q74: =P74*(1+Q73) -> 27329.265 | ... T74: =S74*(1+T73) -> 31335.735
C75: EBIT | G75: =G71-G74 -> 8891 | H75: =H71-H74 -> 7171 | I75: =I71-I74 -> 4917 | J75: =J71-J74 -> 5327.7328 | K75: =K71-K74 -> 6904.3353 | L75: =L71-L74 -> 18236.242 | M75: =M71-M74 -> 23717.611 | N75: =N71-N74 -> 29905.366 | ... T75: =T71-T74 -> 59747.118
C76: EBIT Margin | G76: =G75/G69 -> 0.0918748 | H76: =H75/H69 -> 0.073405671 | I76: =I75/I69 -> 0.051852321 | J76: =J75/J69 -> 0.049170658 | K76: =K75/K69 -> 0.056201925 | L76: =L75/L69 -> 0.13056476 | M76: =M75/M69 -> 0.15025916 | N76: =N75/N69 -> 0.16894925 | ... T76: =T75/T69 -> 0.2174491
C78: Non-Operating (Income) Loss | G78: -1082 | H78: -1914 | I78: -923 | J78: -825 | K78: =$D$64 -> 350 | L78: =$D$64 -> 350 | M78: =$D$64 -> 350 | N78: =$D$64 -> 350 | O78: =$D$64 -> 350 | P78: =$D$64 -> 350 | Q78: =$D$64 -> 350 | R78: =$D$64 -> 350 | ... T78: =$D$64 -> 350 | V78: Assume Non-Operating Income Net 350, (Interest Expense of 350) from 2026 on
C79: EBT | G79: =G75-G78 -> 9973 | H79: =H75-H78 -> 9085 | I79: =I75-I78 -> 5840 | J79: =J75-J78 -> 6152.7328 | K79: =K75-K78 -> 6554.3353 | L79: =L75-L78 -> 17886.242 | M79: =M75-M78 -> 23367.611 | N79: =N75-N78 -> 29555.366 | ... T79: =T75-T78 -> 59397.118
C81: Current Tax | J81: =J203 -> 1678.3525 | K81: =K203 -> 1436.7925 | L81: =L203 -> 875.1325 | M81: =M203 -> 1169.1257 | N81: =N203 -> 1517.9319 | O81: =O203 -> 4285.3141 | P81: =P203 -> 5764.6056 | Q81: =Q203 -> 7394.124 | ... S81: =S203 -> 9519.9485 | T81: =$D$65*T79 -> 13067.366
C82: Deferred Tax | J82: =J204 -> 515.7075 | K82: =K204 -> 561.9075 | L82: =L204 -> 409.6675 | M82: =M204 -> 184.4755 | N82: =N204 -> -75.9781 | O82: =O204 -> -350.34098 | P82: =P204 -> -623.73128 | Q82: =Q204 -> -891.94353 | ... S82: =S204 -> -180.83666 | T82: 0
C83: Total Tax | G83: -5001 | H83: 1837 | I83: 1423 | J83: =J81+J82 -> 2194.06 | K83: =K81+K82 -> 1998.7 | L83: =L81+L82 -> 1284.8 | M83: =M81+M82 -> 1353.6012 | N83: =N81+N82 -> 1441.9538 | O83: =O81+O82 -> 3934.9732 | P83: =P81+P82 -> 5140.8744 | Q83: =Q81+Q82 -> 6502.1804 | ... T83: =T81+T82 -> 13067.366
C85: Net Income | G85: =G79-G83 -> 14974 | H85: =H79-H83 -> 7248 | I85: =I79-I83 -> 4417 | J85: =J79-J83 -> 3958.6728 | K85: =K79-K83 -> 4555.6353 | L85: =L79-L83 -> 16601.442 | M85: =M79-M83 -> 22014.01 | N85: =N79-N83 -> 28113.412 | ... T85: =T79-T83 -> 46329.752
C87: Historical total tax per Tesla FY2025 reconciliation. Interest income on the $44.1bn cash balance is excluded; that balance is credited separately in the equity bridge.
C89: Working Capital Schedule
C91: All figures in USD millions unless stated | G91: 2023 | H91: 2024 | I91: 2025 | J91: =Inputs!H$13 -> 2026 | K91: =Inputs!I$13 -> 2027 | L91: =Inputs!J$13 -> 2028 | M91: =Inputs!K$13 -> 2029 | N91: =Inputs!L$13 -> 2030 | O91: =Inputs!M$13 -> 2031 | P91: =Inputs!N$13 -> 2032 | Q91: =Inputs!O$13 -> 2033 | ... S91: =Inputs!Q$13 -> 2035 | T91: Term
C92: =IF(Inputs!$E$11=1,"Best Case Selected",IF(Inputs!$E$11=2,"Base Case Selected","Worst Case Selected")) -> Base Case Selected
C94: Days in Period | G94: =Inputs!$G$136 -> 365 | H94: =Inputs!$G$136 -> 365 | I94: =Inputs!$G$136 -> 365 | J94: =Inputs!$G$136 -> 365 | K94: =Inputs!$G$136 -> 365 | L94: =Inputs!$G$136 -> 365 | M94: =Inputs!$G$136 -> 365 | N94: =Inputs!$G$136 -> 365 | ... T94: =Inputs!$G$136 -> 365
C95: Revenue | G95: =G27 -> 96773 | H95: =H27 -> 97690 | I95: =I27 -> 94827 | J95: =J27 -> 108351.87 | K95: =K27 -> 122848.73 | L95: =L27 -> 139672.01 | M95: =M27 -> 157844.69 | N95: =N27 -> 177007.98 | ... T95: =T27 -> 274763.7
C96: Cost of Revenues | G96: =G53 -> 79113 | H96: =H53 -> 80240 | I96: =I53 -> 77733 | J96: =J53 -> 88168.2 | K96: =K53 -> 98860.067 | L96: =L53 -> 102301.31 | M96: =M53 -> 113079.19 | N96: =N53 -> 124370.89 | ... T96: =T53 -> 183680.85
C98: Accounts Receivable | E98: (Days) | G98: =(G102/G95)*G$94 -> 13.23117 | H98: =(H102/H95)*H$94 -> 16.507012 | I98: =(I102/I95)*I$94 -> 17.613549 | J98: =Inputs!H73 -> 18 | K98: =Inputs!I73 -> 18 | L98: =Inputs!J73 -> 18 | M98: =Inputs!K73 -> 18 | N98: =Inputs!L73 -> 18 | O98: =Inputs!M73 -> 18 | P98: =Inputs!N73 -> 18 | Q98: =Inputs!O73 -> 18 | ... T98: =Inputs!R73 -> 18
C99: Inventory | E99: (Days) | G99: =(G103/G96)*G$94 -> 62.865648 | H99: =(H103/H96)*H$94 -> 54.663572 | I99: =(I103/I96)*I$94 -> 58.187385 | J99: =Inputs!H74 -> 58 | K99: =Inputs!I74 -> 58 | L99: =Inputs!J74 -> 58 | M99: =Inputs!K74 -> 58 | N99: =Inputs!L74 -> 58 | O99: =Inputs!M74 -> 58 | P99: =Inputs!N74 -> 58 | Q99: =Inputs!O74 -> 58 | ... T99: =Inputs!R74 -> 58
C100: Accounts Payable | E100: (Days) | G100: =(G104/G96)*G$94 -> 66.579639 | H100: =(H104/H96)*H$94 -> 56.742398 | I100: =(I104/I96)*I$94 -> 62.784339 | J100: =Inputs!H75 -> 62 | K100: =Inputs!I75 -> 62 | L100: =Inputs!J75 -> 62 | M100: =Inputs!K75 -> 62 | N100: =Inputs!L75 -> 62 | O100: =Inputs!M75 -> 62 | P100: =Inputs!N75 -> 62 | Q100: =Inputs!O75 -> 62 | ... T100: =Inputs!R75 -> 62
C102: Accounts Receivable | G102: 3508 | H102: 4418 | I102: 4576 | J102: =(J98/J$94)*J95 -> 5343.38 | K102: =(K98/K$94)*K95 -> 6058.2937 | L102: =(L98/L$94)*L95 -> 6887.9345 | M102: =(M98/M$94)*M95 -> 7784.1218 | N102: =(N98/N$94)*N95 -> 8729.1607 | O102: =(O98/O$94)*O95 -> 9672.8726 | P102: =(P98/P$94)*P95 -> 10585.792 | Q102: =(Q98/Q$94)*Q95 -> 11479.138 | ... T102: =(T98/T$94)*T95 -> 13549.991
C103: Inventory | G103: 13626 | H103: 12017 | I103: 12392 | J103: =(J99/J$94)*J96 -> 14010.289 | K103: =(K99/K$94)*K96 -> 15709.271 | L103: =(L99/L$94)*L96 -> 16256.099 | M103: =(M99/M$94)*M96 -> 17968.747 | N103: =(N99/N$94)*N96 -> 19763.045 | O103: =(O99/O$94)*O96 -> 21518.008 | P103: =(P99/P$94)*P96 -> 23211.68 | Q103: =(Q99/Q$94)*Q96 -> 25013.916 | ... T103: =(T99/T$94)*T96 -> 29187.641
C104: Accounts Payable | G104: 14431 | H104: 12474 | I104: 13371 | J104: =(J100/J$94)*J96 -> 14976.516 | K104: =(K100/K$94)*K96 -> 16792.669 | L104: =(L100/L$94)*L96 -> 17377.209 | M104: =(M100/M$94)*M96 -> 19207.971 | N104: =(N100/N$94)*N96 -> 21126.014 | O104: =(O100/O$94)*O96 -> 23002.008 | P104: =(P100/P$94)*P96 -> 24812.485 | Q104: =(Q100/Q$94)*Q96 -> 26739.013 | ... T104: =(T100/T$94)*T96 -> 31200.582
C106: Current Assets | G106: =G102+G103 -> 17134 | H106: =H102+H103 -> 16435 | I106: =I102+I103 -> 16968 | J106: =J102+J103 -> 19353.669 | K106: =K102+K103 -> 21767.565 | L106: =L102+L103 -> 23144.034 | M106: =M102+M103 -> 25752.869 | N106: =N102+N103 -> 28492.206 | ... T106: =T102+T103 -> 42737.632
C107: Current Liabilities | G107: =G104 -> 14431 | H107: =H104 -> 12474 | I107: =I104 -> 13371 | J107: =J104 -> 14976.516 | K107: =K104 -> 16792.669 | L107: =L104 -> 17377.209 | M107: =M104 -> 19207.971 | N107: =N104 -> 21126.014 | ... T107: =T104 -> 31200.582
C108: Net Working Capital | G108: =G106-G107 -> 2703 | H108: =H106-H107 -> 3961 | I108: =I106-I107 -> 3597 | J108: =J106-J107 -> 4377.1532 | K108: =K106-K107 -> 4974.8957 | L108: =L106-L107 -> 5766.8242 | M108: =M106-M107 -> 6544.8979 | N108: =N106-N107 -> 7366.192 | ... T108: =T106-T107 -> 11537.05
C110: Cash from Working Capital Items | H110: =G108-H108 -> -1258 | I110: =H108-I108 -> 364 | J110: =I108-J108 -> -780.15316 | K110: =J108-K108 -> -597.74253 | L110: =K108-L108 -> -791.92853 | M110: =L108-M108 -> -778.07366 | N110: =M108-N108 -> -821.29416 | O110: =N108-O108 -> -822.68005 | ... T110: =S108-T108 -> -497.35294
C112: Working capital per day in the terminal year is held equal to the final forecast year.
C114: Depreciation Schedule
C116: All figures in USD millions unless stated | G116: 2023 | H116: 2024 | I116: 2025 | J116: =Inputs!H$13 -> 2026 | K116: =Inputs!I$13 -> 2027 | L116: =Inputs!J$13 -> 2028 | M116: =Inputs!K$13 -> 2029 | N116: =Inputs!L$13 -> 2030 | O116: =Inputs!M$13 -> 2031 | P116: =Inputs!N$13 -> 2032 | Q116: =Inputs!O$13 -> 2033 | ... S116: =Inputs!Q$13 -> 2035 | T116: Term
C117: =IF(Inputs!$E$11=1,"Best Case Selected",IF(Inputs!$E$11=2,"Base Case Selected","Worst Case Selected")) -> Base Case Selected
C119: Capital Expenditure | G119: 8898 | H119: 11339 | I119: 12923 | J119: =Inputs!H64 -> 24000 | K119: =Inputs!I64 -> 17000 | L119: =Inputs!J64 -> 15000 | M119: =Inputs!K64 -> 14000 | N119: =Inputs!L64 -> 13500 | O119: =Inputs!M64 -> 13500 | P119: =Inputs!N64 -> 14000 | Q119: =Inputs!O64 -> 14500 | ... S119: =Inputs!Q64 -> 15500 | T119: =$T$121 -> 15269.75
C121: Total Depreciation | J121: =J146 -> 6855.875 | K121: =K146 -> 8905.875 | L121: =L146 -> 10505.875 | M121: =M146 -> 11955.875 | N121: =N146 -> 13330.875 | O121: =O146 -> 14680.875 | P121: =P146 -> 16055.875 | Q121: =Q146 -> 17480.875 | ... T121: =T146 -> 15269.75
C123: EXISTING ASSET DEPRECIATION | E123: Years | J123: Percent of Full Year
C124: Useful Life: Existing Assets | E124: =Inputs!$M$143 -> 8
C125: PP&E and Energy Assets at End of 2025 | E125: =Inputs!$M$133 -> 45247 | J125: =MIN($E$124-SUM($I$125:I125),1) -> 1 | K125: =MIN($E$124-SUM($I$125:J125),1) -> 1 | L125: =MIN($E$124-SUM($I$125:K125),1) -> 1 | M125: =MIN($E$124-SUM($I$125:L125),1) -> 1 | N125: =MIN($E$124-SUM($I$125:M125),1) -> 1 | O125: =MIN($E$124-SUM($I$125:N125),1) -> 1 | P125: =MIN($E$124-SUM($I$125:O125),1) -> 1 | Q125: =MIN($E$124-SUM($I$125:P125),1) -> 1 | ... S125: =MIN($E$124-SUM($I$125:R125),1) -> 0
C127: NEW ASSET DEPRECIATION | E127: Years
C128: Useful Life: New Assets | E128: =Inputs!$M$144 -> 10
C129: First Year Accounting Depreciation | E129: =Inputs!$M$142 -> 0.5
G131: Year | H131: Capex | I131: Per Year | J131: =J$116 -> 2026 | K131: =K$116 -> 2027 | L131: =L$116 -> 2028 | M131: =M$116 -> 2029 | N131: =N$116 -> 2030 | O131: =O$116 -> 2031 | P131: =P$116 -> 2032 | Q131: =Q$116 -> 2033 | ... S131: =S$116 -> 2035
G132: =J$116 -> 2026 | H132: =SUMIF($J$116:$S$116,$G132,$J$119:$S$119) -> 24000 | I132: =$H132/$E$128 -> 2400 | J132: =IF(J$116<$G132,0,IF(J$116=$G132,$I132*$E$129,$I132)) -> 1200 | K132: =IF(K$116<$G132,0,IF(K$116=$G132,$I132*$E$129,$I132)) -> 2400 | L132: =IF(L$116<$G132,0,IF(L$116=$G132,$I132*$E$129,$I132)) -> 2400 | M132: =IF(M$116<$G132,0,IF(M$116=$G132,$I132*$E$129,$I132)) -> 2400 | N132: =IF(N$116<$G132,0,IF(N$116=$G132,$I132*$E$129,$I132)) -> 2400 | O132: =IF(O$116<$G132,0,IF(O$116=$G132,$I132*$E$129,$I132)) -> 2400 | P132: =IF(P$116<$G132,0,IF(P$116=$G132,$I132*$E$129,$I132)) -> 2400 | Q132: =IF(Q$116<$G132,0,IF(Q$116=$G132,$I132*$E$129,$I132)) -> 2400 | ... S132: =IF(S$116<$G132,0,IF(S$116=$G132,$I132*$E$129,$I132)) -> 2400
G133: =K$116 -> 2027 | H133: =SUMIF($J$116:$S$116,$G133,$J$119:$S$119) -> 17000 | I133: =$H133/$E$128 -> 1700 | J133: =IF(J$116<$G133,0,IF(J$116=$G133,$I133*$E$129,$I133)) -> 0 | K133: =IF(K$116<$G133,0,IF(K$116=$G133,$I133*$E$129,$I133)) -> 850 | L133: =IF(L$116<$G133,0,IF(L$116=$G133,$I133*$E$129,$I133)) -> 1700 | M133: =IF(M$116<$G133,0,IF(M$116=$G133,$I133*$E$129,$I133)) -> 1700 | N133: =IF(N$116<$G133,0,IF(N$116=$G133,$I133*$E$129,$I133)) -> 1700 | O133: =IF(O$116<$G133,0,IF(O$116=$G133,$I133*$E$129,$I133)) -> 1700 | P133: =IF(P$116<$G133,0,IF(P$116=$G133,$I133*$E$129,$I133)) -> 1700 | Q133: =IF(Q$116<$G133,0,IF(Q$116=$G133,$I133*$E$129,$I133)) -> 1700 | ... S133: =IF(S$116<$G133,0,IF(S$116=$G133,$I133*$E$129,$I133)) -> 1700
G134: =L$116 -> 2028 | H134: =SUMIF($J$116:$S$116,$G134,$J$119:$S$119) -> 15000 | I134: =$H134/$E$128 -> 1500 | J134: =IF(J$116<$G134,0,IF(J$116=$G134,$I134*$E$129,$I134)) -> 0 | K134: =IF(K$116<$G134,0,IF(K$116=$G134,$I134*$E$129,$I134)) -> 0 | L134: =IF(L$116<$G134,0,IF(L$116=$G134,$I134*$E$129,$I134)) -> 750 | M134: =IF(M$116<$G134,0,IF(M$116=$G134,$I134*$E$129,$I134)) -> 1500 | N134: =IF(N$116<$G134,0,IF(N$116=$G134,$I134*$E$129,$I134)) -> 1500 | O134: =IF(O$116<$G134,0,IF(O$116=$G134,$I134*$E$129,$I134)) -> 1500 | P134: =IF(P$116<$G134,0,IF(P$116=$G134,$I134*$E$129,$I134)) -> 1500 | Q134: =IF(Q$116<$G134,0,IF(Q$116=$G134,$I134*$E$129,$I134)) -> 1500 | ... S134: =IF(S$116<$G134,0,IF(S$116=$G134,$I134*$E$129,$I134)) -> 1500
G135: =M$116 -> 2029 | H135: =SUMIF($J$116:$S$116,$G135,$J$119:$S$119) -> 14000 | I135: =$H135/$E$128 -> 1400 | J135: =IF(J$116<$G135,0,IF(J$116=$G135,$I135*$E$129,$I135)) -> 0 | K135: =IF(K$116<$G135,0,IF(K$116=$G135,$I135*$E$129,$I135)) -> 0 | L135: =IF(L$116<$G135,0,IF(L$116=$G135,$I135*$E$129,$I135)) -> 0 | M135: =IF(M$116<$G135,0,IF(M$116=$G135,$I135*$E$129,$I135)) -> 700 | N135: =IF(N$116<$G135,0,IF(N$116=$G135,$I135*$E$129,$I135)) -> 1400 | O135: =IF(O$116<$G135,0,IF(O$116=$G135,$I135*$E$129,$I135)) -> 1400 | P135: =IF(P$116<$G135,0,IF(P$116=$G135,$I135*$E$129,$I135)) -> 1400 | Q135: =IF(Q$116<$G135,0,IF(Q$116=$G135,$I135*$E$129,$I135)) -> 1400 | ... S135: =IF(S$116<$G135,0,IF(S$116=$G135,$I135*$E$129,$I135)) -> 1400
G136: =N$116 -> 2030 | H136: =SUMIF($J$116:$S$116,$G136,$J$119:$S$119) -> 13500 | I136: =$H136/$E$128 -> 1350 | J136: =IF(J$116<$G136,0,IF(J$116=$G136,$I136*$E$129,$I136)) -> 0 | K136: =IF(K$116<$G136,0,IF(K$116=$G136,$I136*$E$129,$I136)) -> 0 | L136: =IF(L$116<$G136,0,IF(L$116=$G136,$I136*$E$129,$I136)) -> 0 | M136: =IF(M$116<$G136,0,IF(M$116=$G136,$I136*$E$129,$I136)) -> 0 | N136: =IF(N$116<$G136,0,IF(N$116=$G136,$I136*$E$129,$I136)) -> 675 | O136: =IF(O$116<$G136,0,IF(O$116=$G136,$I136*$E$129,$I136)) -> 1350 | P136: =IF(P$116<$G136,0,IF(P$116=$G136,$I136*$E$129,$I136)) -> 1350 | Q136: =IF(Q$116<$G136,0,IF(Q$116=$G136,$I136*$E$129,$I136)) -> 1350 | ... S136: =IF(S$116<$G136,0,IF(S$116=$G136,$I136*$E$129,$I136)) -> 1350
G137: =O$116 -> 2031 | H137: =SUMIF($J$116:$S$116,$G137,$J$119:$S$119) -> 13500 | I137: =$H137/$E$128 -> 1350 | J137: =IF(J$116<$G137,0,IF(J$116=$G137,$I137*$E$129,$I137)) -> 0 | K137: =IF(K$116<$G137,0,IF(K$116=$G137,$I137*$E$129,$I137)) -> 0 | L137: =IF(L$116<$G137,0,IF(L$116=$G137,$I137*$E$129,$I137)) -> 0 | M137: =IF(M$116<$G137,0,IF(M$116=$G137,$I137*$E$129,$I137)) -> 0 | N137: =IF(N$116<$G137,0,IF(N$116=$G137,$I137*$E$129,$I137)) -> 0 | O137: =IF(O$116<$G137,0,IF(O$116=$G137,$I137*$E$129,$I137)) -> 675 | P137: =IF(P$116<$G137,0,IF(P$116=$G137,$I137*$E$129,$I137)) -> 1350 | Q137: =IF(Q$116<$G137,0,IF(Q$116=$G137,$I137*$E$129,$I137)) -> 1350 | ... S137: =IF(S$116<$G137,0,IF(S$116=$G137,$I137*$E$129,$I137)) -> 1350
G138: =P$116 -> 2032 | H138: =SUMIF($J$116:$S$116,$G138,$J$119:$S$119) -> 14000 | I138: =$H138/$E$128 -> 1400 | J138: =IF(J$116<$G138,0,IF(J$116=$G138,$I138*$E$129,$I138)) -> 0 | K138: =IF(K$116<$G138,0,IF(K$116=$G138,$I138*$E$129,$I138)) -> 0 | L138: =IF(L$116<$G138,0,IF(L$116=$G138,$I138*$E$129,$I138)) -> 0 | M138: =IF(M$116<$G138,0,IF(M$116=$G138,$I138*$E$129,$I138)) -> 0 | N138: =IF(N$116<$G138,0,IF(N$116=$G138,$I138*$E$129,$I138)) -> 0 | O138: =IF(O$116<$G138,0,IF(O$116=$G138,$I138*$E$129,$I138)) -> 0 | P138: =IF(P$116<$G138,0,IF(P$116=$G138,$I138*$E$129,$I138)) -> 700 | Q138: =IF(Q$116<$G138,0,IF(Q$116=$G138,$I138*$E$129,$I138)) -> 1400 | ... S138: =IF(S$116<$G138,0,IF(S$116=$G138,$I138*$E$129,$I138)) -> 1400
G139: =Q$116 -> 2033 | H139: =SUMIF($J$116:$S$116,$G139,$J$119:$S$119) -> 14500 | I139: =$H139/$E$128 -> 1450 | J139: =IF(J$116<$G139,0,IF(J$116=$G139,$I139*$E$129,$I139)) -> 0 | K139: =IF(K$116<$G139,0,IF(K$116=$G139,$I139*$E$129,$I139)) -> 0 | L139: =IF(L$116<$G139,0,IF(L$116=$G139,$I139*$E$129,$I139)) -> 0 | M139: =IF(M$116<$G139,0,IF(M$116=$G139,$I139*$E$129,$I139)) -> 0 | N139: =IF(N$116<$G139,0,IF(N$116=$G139,$I139*$E$129,$I139)) -> 0 | O139: =IF(O$116<$G139,0,IF(O$116=$G139,$I139*$E$129,$I139)) -> 0 | P139: =IF(P$116<$G139,0,IF(P$116=$G139,$I139*$E$129,$I139)) -> 0 | Q139: =IF(Q$116<$G139,0,IF(Q$116=$G139,$I139*$E$129,$I139)) -> 725 | ... S139: =IF(S$116<$G139,0,IF(S$116=$G139,$I139*$E$129,$I139)) -> 1450
G140: =R$116 -> 2034 | H140: =SUMIF($J$116:$S$116,$G140,$J$119:$S$119) -> 15000 | I140: =$H140/$E$128 -> 1500 | J140: =IF(J$116<$G140,0,IF(J$116=$G140,$I140*$E$129,$I140)) -> 0 | K140: =IF(K$116<$G140,0,IF(K$116=$G140,$I140*$E$129,$I140)) -> 0 | L140: =IF(L$116<$G140,0,IF(L$116=$G140,$I140*$E$129,$I140)) -> 0 | M140: =IF(M$116<$G140,0,IF(M$116=$G140,$I140*$E$129,$I140)) -> 0 | N140: =IF(N$116<$G140,0,IF(N$116=$G140,$I140*$E$129,$I140)) -> 0 | O140: =IF(O$116<$G140,0,IF(O$116=$G140,$I140*$E$129,$I140)) -> 0 | P140: =IF(P$116<$G140,0,IF(P$116=$G140,$I140*$E$129,$I140)) -> 0 | Q140: =IF(Q$116<$G140,0,IF(Q$116=$G140,$I140*$E$129,$I140)) -> 0 | ... S140: =IF(S$116<$G140,0,IF(S$116=$G140,$I140*$E$129,$I140)) -> 1500
G141: =S$116 -> 2035 | H141: =SUMIF($J$116:$S$116,$G141,$J$119:$S$119) -> 15500 | I141: =$H141/$E$128 -> 1550 | J141: =IF(J$116<$G141,0,IF(J$116=$G141,$I141*$E$129,$I141)) -> 0 | K141: =IF(K$116<$G141,0,IF(K$116=$G141,$I141*$E$129,$I141)) -> 0 | L141: =IF(L$116<$G141,0,IF(L$116=$G141,$I141*$E$129,$I141)) -> 0 | M141: =IF(M$116<$G141,0,IF(M$116=$G141,$I141*$E$129,$I141)) -> 0 | N141: =IF(N$116<$G141,0,IF(N$116=$G141,$I141*$E$129,$I141)) -> 0 | O141: =IF(O$116<$G141,0,IF(O$116=$G141,$I141*$E$129,$I141)) -> 0 | P141: =IF(P$116<$G141,0,IF(P$116=$G141,$I141*$E$129,$I141)) -> 0 | Q141: =IF(Q$116<$G141,0,IF(Q$116=$G141,$I141*$E$129,$I141)) -> 0 | ... S141: =IF(S$116<$G141,0,IF(S$116=$G141,$I141*$E$129,$I141)) -> 775
C143: TOTAL ASSET DEPRECIATION
C144: Existing Assets | J144: =($E$125/$E$124)*J125 -> 5655.875 | K144: =($E$125/$E$124)*K125 -> 5655.875 | L144: =($E$125/$E$124)*L125 -> 5655.875 | M144: =($E$125/$E$124)*M125 -> 5655.875 | N144: =($E$125/$E$124)*N125 -> 5655.875 | O144: =($E$125/$E$124)*O125 -> 5655.875 | P144: =($E$125/$E$124)*P125 -> 5655.875 | Q144: =($E$125/$E$124)*Q125 -> 5655.875 | ... S144: =($E$125/$E$124)*S125 -> 0
C145: New Assets | J145: =SUM(J132:J141) -> 1200 | K145: =SUM(K132:K141) -> 3250 | L145: =SUM(L132:L141) -> 4850 | M145: =SUM(M132:M141) -> 6300 | N145: =SUM(N132:N141) -> 7675 | O145: =SUM(O132:O141) -> 9025 | P145: =SUM(P132:P141) -> 10400 | Q145: =SUM(Q132:Q141) -> 11825 | ... S145: =SUM(S132:S141) -> 14825
C146: Total Depreciation | J146: =J144+J145 -> 6855.875 | K146: =K144+K145 -> 8905.875 | L146: =L144+L145 -> 10505.875 | M146: =M144+M145 -> 11955.875 | N146: =N144+N145 -> 13330.875 | O146: =O144+O145 -> 14680.875 | P146: =P144+P145 -> 16055.875 | Q146: =Q144+Q145 -> 17480.875 | ... S146: =S144+S145 -> 14825 | T146: =$S$146*(1+Inputs!$G$142) -> 15269.75
C148: Straight-line depreciation. All PP&E and capital expenditure is assumed depreciable, with a half-year convention in the year of spend.
C149: Terminal-year depreciation is grown at the terminal growth rate and capital expenditure is set equal to it.
...

Sheet Relative Valuation
C1: AMIR J
D5: Relative Valuation: Peer Group Multiples
D7: All figures in USD millions unless stated. Multiples are on an FY2026 estimated basis.
D8: Peer set selected on business-model comparability: EV manufacturing, exposure to autonomy software, and scale global OEMs.
D10: Peer Company | E10: Basis for Inclusion | F10: EV / Sales | G10: EV / EBITDA | H10: P / E
D12: BYD Company Ltd. | E12: China EV / vertically integrated | F12: 1 | G12: 6.7 | H12: 16
D13: Li Auto Inc. | E13: China EV / premium NEV | F13: 0.2 | G13: 2.5 | H13: 39.1
D14: XPeng Inc. | E14: China EV / ADAS-led | F14: 5.8 | G14: - | H14: -
D15: NIO Inc. | E15: China EV / battery swap | F15: 0.6 | G15: 8.4 | H15: 63.4
D16: Rivian Automotive Inc. | E16: US EV pure play | F16: 2.6 | G16: - | H16: -
D17: Lucid Group Inc. | E17: US EV pure play | F17: 2.5 | G17: - | H17: -
D18: General Motors Co. | E18: US legacy OEM / EV transition | F18: 0.4 | G18: 3.2 | H18: 6.4
D19: Ford Motor Co. | E19: US legacy OEM / EV transition | F19: 2.5 | G19: 3.8 | H19: 8
D21: Peer Mean | F21: =AVERAGE(F12:F19) -> 1.95 | G21: =AVERAGE(G12:G19) -> 4.92 | H21: =AVERAGE(H12:H19) -> 26.58
D22: Peer Median | F22: =MEDIAN(F12:F19) -> 1.75 | G22: =MEDIAN(G12:G19) -> 3.8 | H22: =MEDIAN(H12:H19) -> 16
D24: Tesla, Inc. (at market) | E24: Current trading multiples | F24: =$F$33/Model!$J$27 -> 9.7875734 | G24: =$F$33/Model!$J$256 -> 87.043338 | H24: =Inputs!$G$141/(Model!$J$85/Inputs!$G$140) -> 276.90717
D26: Peer multiples are analyst-compiled estimates and should be refreshed against a live data terminal before publication.
D27: Six of nine peers are loss-making or marginally profitable, so EV/Sales is the only multiple available across the full set.
D28: Implied Valuation from Peer Multiples
D29: Applied to Tesla FY2026 estimated metrics from the operating model, base case (switch = 2).
D31: Metric | E31: FY2026E Tesla Metric | F31: Enterprise Value | G31: Equity Value | H31: Value per Share | I31: Premium / (Discount)
D33: Market Enterprise Value | E33: Current market capitalisation | F33: =Inputs!$G$140*Inputs!$G$141+Inputs!$M$132 -> 1060501.9 | G33: =Inputs!$G$140*Inputs!$G$141 -> 1096184.9 | H33: =Inputs!$G$141 -> 309.22 | I33: 0
D35: Peer Median EV / Sales | E35: =Model!$J$27 -> 108351.87 | F35: =E35*$F$22 -> 189615.78 | G35: =F35-Inputs!$M$132 -> 225298.78 | H35: =G35/Inputs!$G$140 -> 63.553957 | I35: =H35/Inputs!$G$141-1 -> -0.7944701
D36: Peer Median EV / EBITDA | E36: =Model!$J$256 -> 12183.608 | F36: =E36*$G$22 -> 46297.71 | G36: =F36-Inputs!$M$132 -> 81980.71 | H36: =G36/Inputs!$G$140 -> 23.125729 | I36: =H36/Inputs!$G$141-1 -> -0.9252127
D37: Peer Mean EV / Sales | E37: =Model!$J$27 -> 108351.87 | F37: =E37*$F$21 -> 211286.15 | G37: =F37-Inputs!$M$132 -> 246969.15 | H37: =G37/Inputs!$G$140 -> 69.666897 | I37: =H37/Inputs!$G$141-1 -> -0.77470119
D38: Peer Mean EV / EBITDA | E38: =Model!$J$256 -> 12183.608 | F38: =E38*$G$21 -> 59943.351 | G38: =F38-Inputs!$M$132 -> 95626.351 | H38: =G38/Inputs!$G$140 -> 26.974993 | I38: =H38/Inputs!$G$141-1 -> -0.9127644
D40: Growth-Adjusted Premium Applied | E40: 1 | G40: Premium to peer median EV/EBITDA to reflect Tesla's superior growth and software mix.
D41: Premium-Adjusted EV / EBITDA | E41: =Model!$J$256 -> 12183.608 | F41: =E41*$G$22*(1+$E$40) -> 92595.42 | G41: =F41-Inputs!$M$132 -> 128278.42 | H41: =G41/Inputs!$G$140 -> 36.185732 | I41: =H41/Inputs!$G$141-1 -> -0.88297739
D43: Tesla's FY2026E EBITDA is depressed by an elevated investment phase, which flatters the implied EV/EBITDA multiple relative to peers.
D45: Valuation Summary and Recommendation
D48: Methodology | E48: Weighting | F48: Enterprise Value | G48: Equity Value | H48: Value per Share | I48: Premium / (Discount)
D50: DCF - Perpetuity Growth Method | E50: 0.4 | F50: =Model!$I$307 -> 616187.58 | G50: =F50-Inputs!$M$132 -> 651870.58 | H50: =G50/Inputs!$G$140 -> 183.88451 | I50: =H50/Inputs!$G$141-1 -> -0.4053279
D51: DCF - Terminal Multiple Method | E51: 0.35 | F51: =Model!$I$349 -> 589784.74 | G51: =F51-Inputs!$M$132 -> 625467.74 | H51: =G51/Inputs!$G$140 -> 176.4366 | I51: =H51/Inputs!$G$141-1 -> -0.42941401
D52: Relative - Peer Median EV/EBITDA (premium adjusted) | E52: 0.25 | F52: =$F$41 -> 92595.42 | G52: =F52-Inputs!$M$132 -> 128278.42 | H52: =G52/Inputs!$G$140 -> 36.185732 | I52: =H52/Inputs!$G$141-1 -> -0.88297739
D54: Weighted Fair Value | E54: =SUM(E50:E52) -> 1 | F54: =SUMPRODUCT(E50:E52,F50:F52) -> 476048.54 | G54: =F54-Inputs!$M$132 -> 511731.54 | H54: =G54/Inputs!$G$140 -> 144.35305 | I54: =H54/Inputs!$G$141-1 -> -0.53317041
D56: Current Share Price | H56: =Inputs!$G$141 -> 309.22
D58: Recommendation | E58: =IF(H54/Inputs!$G$141-1>0.15,"BUY",IF(H54/Inputs!$G$141-1<-0.15,"SELL","HOLD")) -> SELL | G58: Threshold: BUY above +15%, SELL below -15%, otherwise HOLD.
D64: Valuation Range | H64: =Outputs!$I$18 -> 61.226639
D65: Low (Worst Case, Perpetuity) | H65: =H54 -> 144.35305
D66: Central (Base Case, Weighted) | H66: =Outputs!$I$16 -> 417.31841
D67: High (Best Case, Perpetuity)
D69: The gap between the fundamental range and the market price represents the value the market ascribes to autonomy, robotics and energy optionality not underwritten in the base case.
